{"name": "SimpleSQLite", "run_requires": [{"requires": ["DataProperty (>=0.7.0)", "jsonschema", "pathvalidate (>=0.4.2)", "path.py", "six", "xlrd"]}], "generator": "bdist_wheel (0.24.0)", "test_requires": [{"requires": ["pytest-cov", "pytest", "tox", "XlsxWriter"]}], "summary": "SimpleSQLite is a python library to simplify the table creation and data insertion in SQLite database.", "metadata_version": "2.0", "version": "0.4.2", "extensions": {"python.details": {"document_names": {"description": "DESCRIPTION.rst"}}}, "extras": []}