{"download_url": "https://github.com/hartym/django-includes/archive/0.1.1.tar.gz", "extensions": {"python.details": {"document_names": {"description": "DESCRIPTION.rst"}, "project_urls": {"Home": "https://github.com/hartym/django-includes"}}}, "extras": ["dev"], "generator": "bdist_wheel (0.29.0)", "license": "Apache License, Version 2.0", "metadata_version": "2.0", "name": "django-includes", "run_requires": [{"requires": ["CacheControl (>=0.11.6,<0.12)", "PyJWT (>=1.4,<1.5)", "django (>=1.9)", "edgy.event (<0.2,>=0.1)", "jinja2 (>=2.7,<3.0)", "requests (<2.10,>=2.9.1)", "six"]}, {"extra": "dev", "requires": ["coverage (>=4.0,<4.2)", "mock (>=1.3,<1.4)", "nose (>=1.3,<1.4)", "pylint (>=1.4,<1.5)", "pytest (>=2.8,<2.9)", "pytest-cov (>=2.2,<2.3)", "sphinx-rtd-theme", "sphinx"]}], "summary": "UNKNOWN", "version": "0.1.1"}